dramcash_lib/__init__.py
dramcash_lib/config.py
dramcash_lib/constants.py
dramcash_lib/logger.py
dramcash_lib/message.py
dramcash_lib-0.1.5.dist-info/METADATA
dramcash_lib-0.1.5.dist-info/WHEEL
dramcash_lib-0.1.5.dist-info/top_level.txt
dramcash_lib-0.1.5.dist-info/RECORD
