Metadata-Version: 2.4
Name: dramcash_lib
Version: 0.1.5
Summary: Shared utility library for all microservices
Home-page: https://github.com/sudhinm/dramcash_lib
Author: Sudhin M
Author-email: sudhin.m@abilytics.com
Classifier: Programming Language :: Python :: 3
Classifier: License :: OSI Approved :: MIT License
Classifier: Operating System :: OS Independent
Requires-Python: >=3.8
Requires-Dist: boto3
Requires-Dist: pydantic-settings
Dynamic: author
Dynamic: author-email
Dynamic: classifier
Dynamic: description
Dynamic: description-content-type
Dynamic: home-page
Dynamic: requires-dist
Dynamic: requires-python
Dynamic: summary
